[
  {
    "title": "13 Girls",
    "url": "https://www.adultempire.com/96104/studio/13-girls-porn-movies.html",
    "num_dvds": 25
  },
  {
    "title": "18 Carat",
    "url": "https://www.adultempire.com/90723/studio/18-carat-porn-movies.html",
    "num_dvds": 13
  },
  {
    "title": "2020 Vision",
    "url": "https://www.adultempire.com/95898/studio/2020-vision-porn-movies.html",
    "num_dvds": 25
  },
  {
    "title": "21 Sextury Video",
    "url": "https://www.adultempire.com/89475/studio/21-sextury-video-porn-movies.html",
    "num_dvds": 157
  },
  {
    "title": "21 Sextury Video (Pulse)",
    "url": "https://www.adultempire.com/93626/studio/21-sextury-video-pulse-porn-movies.html",
    "num_dvds": 628
  },
  {
    "title": "310",
    "url": "https://www.adultempire.com/93286/studio/310-porn-movies.html",
    "num_dvds": 31
  },
  {
    "title": "6 Hour Series",
    "url": "https://www.adultempire.com/95767/studio/6-hour-series-porn-movies.html",
    "num_dvds": 5
  },
  {
    "title": "6AM Classixxx",
    "url": "https://www.adultempire.com/96340/studio/6am-classixxx-porn-movies.html",
    "num_dvds": 68
  },
  {
    "title": "6AM Double Feature",
    "url": "https://www.adultempire.com/98402/studio/6am-double-feature-porn-movies.html",
    "num_dvds": 14
  },
  {
    "title": "6AM Studios",
    "url": "https://www.adultempire.com/95625/studio/6am-studios-porn-movies.html",
    "num_dvds": 411
  },
  {
    "title": "818 XXX",
    "url": "https://www.adultempire.com/93145/studio/818-xxx-porn-movies.html",
    "num_dvds": 54
  },
  {
    "title": "abbywinters",
    "url": "https://www.adultempire.com/92764/studio/abbywinters-porn-movies.html",
    "num_dvds": 596
  },
  {
    "title": "Abigail Productions",
    "url": "https://www.adultempire.com/92910/studio/abigail-productions-porn-movies.html",
    "num_dvds": 102
  },
  {
    "title": "Ablaze Productions",
    "url": "https://www.adultempire.com/93985/studio/ablaze-productions-porn-movies.html",
    "num_dvds": 10
  },
  {
    "title": "Absolute Amateurs",
    "url": "https://www.adultempire.com/93401/studio/absolute-amateurs-porn-movies.html",
    "num_dvds": 4
  },
  {
    "title": "Absolute Jewel",
    "url": "https://www.adultempire.com/93288/studio/absolute-jewel-porn-movies.html",
    "num_dvds": 12
  },
  {
    "title": "Ace In The Hole",
    "url": "https://www.adultempire.com/94163/studio/ace-in-the-hole-porn-movies.html",
    "num_dvds": 112
  },
  {
    "title": "Acid Rain",
    "url": "https://www.adultempire.com/27208/studio/acid-rain-porn-movies.html",
    "num_dvds": 584
  },
  {
    "title": "Adam & Eve",
    "url": "https://www.adultempire.com/155/studio/adam-eve-porn-movies.html",
    "num_dvds": 1154
  },
  {
    "title": "Addicted 2 Girls",
    "url": "https://www.adultempire.com/93760/studio/addicted-2-girls-porn-movies.html",
    "num_dvds": 83
  },
  {
    "title": "Adorable Teens",
    "url": "https://www.adultempire.com/94789/studio/adorable-teens-porn-movies.html",
    "num_dvds": 4
  },
  {
    "title": "Adult Source Media",
    "url": "https://www.adultempire.com/31352/studio/adult-source-media-porn-movies.html",
    "num_dvds": 236
  },
  {
    "title": "Adult Time",
    "url": "https://www.adultempire.com/95569/studio/adult-time-porn-movies.html",
    "num_dvds": 176
  },
  {
    "title": "AE Films",
    "url": "https://www.adultempire.com/94031/studio/ae-films-porn-movies.html",
    "num_dvds": 13
  },
  {
    "title": "Afro-Centric Productions",
    "url": "https://www.adultempire.com/93031/studio/afro-centric-productions-porn-movies.html",
    "num_dvds": 26
  },
  {
    "title": "After Hours Cinema",
    "url": "https://www.adultempire.com/89375/studio/after-hours-cinema-porn-movies.html",
    "num_dvds": 8
  },
  {
    "title": "After Hours Cinema (Adult)",
    "url": "https://www.adultempire.com/92943/studio/after-hours-cinema-adult-porn-movies.html",
    "num_dvds": 28
  },
  {
    "title": "AGW Entertainment",
    "url": "https://www.adultempire.com/94055/studio/agw-entertainment-porn-movies.html",
    "num_dvds": 18
  },
  {
    "title": "Airerose Entertainment",
    "url": "https://www.adultempire.com/93969/studio/airerose-entertainment-porn-movies.html",
    "num_dvds": 257
  },
  {
    "title": "Alborda Video",
    "url": "https://www.adultempire.com/325/studio/alborda-video-porn-movies.html",
    "num_dvds": 31
  },
  {
    "title": "Alex Romero",
    "url": "https://www.adultempire.com/93851/studio/alex-romero-porn-movies.html",
    "num_dvds": 104
  },
  {
    "title": "Alexander DeVoe Video",
    "url": "https://www.adultempire.com/93857/studio/alexander-devoe-video-porn-movies.html",
    "num_dvds": 46
  },
  {
    "title": "Alexander Institute (Adult)",
    "url": "https://www.adultempire.com/28205/studio/alexander-institute-adult-porn-movies.html",
    "num_dvds": 42
  },
  {
    "title": "Alexis Golden Productions",
    "url": "https://www.adultempire.com/93659/studio/alexis-golden-productions-porn-movies.html",
    "num_dvds": 11
  },
  {
    "title": "All Anal",
    "url": "https://www.adultempire.com/95929/studio/all-anal-porn-movies.html",
    "num_dvds": 13
  },
  {
    "title": "All Black X",
    "url": "https://www.adultempire.com/95969/studio/all-black-x-porn-movies.html",
    "num_dvds": 20
  },
  {
    "title": "All Her Luv (AllHerLuv)",
    "url": "https://www.adultempire.com/95353/studio/all-her-luv-allherluv-porn-movies.html",
    "num_dvds": 7
  },
  {
    "title": "All Niche Productions",
    "url": "https://www.adultempire.com/94256/studio/all-niche-productions-porn-movies.html",
    "num_dvds": 368
  },
  {
    "title": "All Worlds Video",
    "url": "https://www.adultempire.com/394/studio/all-worlds-video-porn-movies.html",
    "num_dvds": 14
  },
  {
    "title": "Allure Films",
    "url": "https://www.adultempire.com/94959/studio/allure-films-porn-movies.html",
    "num_dvds": 70
  },
  {
    "title": "Alpha Blue Archives",
    "url": "https://www.adultempire.com/23045/studio/alpha-blue-archives-porn-movies.html",
    "num_dvds": 421
  },
  {
    "title": "Alpha-France",
    "url": "https://www.adultempire.com/93959/studio/alpha-france-porn-movies.html",
    "num_dvds": 83
  },
  {
    "title": "Alternative Cinema",
    "url": "https://www.adultempire.com/85695/studio/alternative-cinema-porn-movies.html",
    "num_dvds": 9
  },
  {
    "title": "AltErotic",
    "url": "https://www.adultempire.com/95561/studio/alterotic-porn-movies.html",
    "num_dvds": 33
  },
  {
    "title": "Amateur Allure",
    "url": "https://www.adultempire.com/93862/studio/amateur-allure-porn-movies.html",
    "num_dvds": 113
  },
  {
    "title": "Amateur District",
    "url": "https://www.adultempire.com/91570/studio/amateur-district-porn-movies.html",
    "num_dvds": 41
  },
  {
    "title": "Amateur Hall of Fame Productions",
    "url": "https://www.adultempire.com/93660/studio/amateur-hall-of-fame-productions-porn-movies.html",
    "num_dvds": 4
  },
  {
    "title": "Amateur XXX",
    "url": "https://www.adultempire.com/94001/studio/amateur-xxx-porn-movies.html",
    "num_dvds": 144
  },
  {
    "title": "Amateurs Recorded",
    "url": "https://www.adultempire.com/96369/studio/amateurs-recorded-porn-movies.html",
    "num_dvds": 34
  },
  {
    "title": "American Hardcore",
    "url": "https://www.adultempire.com/34994/studio/american-hardcore-porn-movies.html",
    "num_dvds": 15
  },
  {
    "title": "American Honey",
    "url": "https://www.adultempire.com/95128/studio/american-honey-porn-movies.html",
    "num_dvds": 5
  },
  {
    "title": "AMK Empire",
    "url": "https://www.adultempire.com/93684/studio/amk-empire-porn-movies.html",
    "num_dvds": 415
  },
  {
    "title": "Amorz",
    "url": "https://www.adultempire.com/93228/studio/amorz-porn-movies.html",
    "num_dvds": 780
  },
  {
    "title": "Amsterdam Amateurs",
    "url": "https://www.adultempire.com/96526/studio/amsterdam-amateurs-porn-movies.html",
    "num_dvds": 42
  },
  {
    "title": "Anabolic Video",
    "url": "https://www.adultempire.com/170/studio/anabolic-video-porn-movies.html",
    "num_dvds": 492
  },
  {
    "title": "Anal Industries",
    "url": "https://www.adultempire.com/93804/studio/anal-industries-porn-movies.html",
    "num_dvds": 80
  },
  {
    "title": "Anal Only",
    "url": "https://www.adultempire.com/96176/studio/anal-only-porn-movies.html",
    "num_dvds": 12
  },
  {
    "title": "Analized",
    "url": "https://www.adultempire.com/95120/studio/analized-porn-movies.html",
    "num_dvds": 97
  },
  {
    "title": "Anarchy Films",
    "url": "https://www.adultempire.com/21569/studio/anarchy-films-porn-movies.html",
    "num_dvds": 286
  },
  {
    "title": "Anastasia Pierce Productions",
    "url": "https://www.adultempire.com/36194/studio/anastasia-pierce-productions-porn-movies.html",
    "num_dvds": 53
  },
  {
    "title": "Anatomik Media",
    "url": "https://www.adultempire.com/95051/studio/anatomik-media-porn-movies.html",
    "num_dvds": 22
  },
  {
    "title": "Andrew Blake",
    "url": "https://www.adultempire.com/160/studio/andrew-blake-porn-movies.html",
    "num_dvds": 52
  },
  {
    "title": "Anilos",
    "url": "https://www.adultempire.com/94818/studio/anilos-porn-movies.html",
    "num_dvds": 23
  },
  {
    "title": "Anime Erotica",
    "url": "https://www.adultempire.com/92002/studio/anime-erotica-porn-movies.html",
    "num_dvds": 5
  },
  {
    "title": "Anna Bell Peaks",
    "url": "https://www.adultempire.com/95143/studio/anna-bell-peaks-porn-movies.html",
    "num_dvds": 6
  },
  {
    "title": "Antigua Pictures",
    "url": "https://www.adultempire.com/31351/studio/antigua-pictures-porn-movies.html",
    "num_dvds": 103
  },
  {
    "title": "Apex Films",
    "url": "https://www.adultempire.com/96204/studio/apex-films-porn-movies.html",
    "num_dvds": 46
  },
  {
    "title": "ArchAngel",
    "url": "https://www.adultempire.com/94082/studio/archangel-porn-movies.html",
    "num_dvds": 124
  },
  {
    "title": "Arousins",
    "url": "https://www.adultempire.com/98382/studio/arousins-porn-movies.html",
    "num_dvds": 12
  },
  {
    "title": "Arrow Productions",
    "url": "https://www.adultempire.com/150/studio/arrow-productions-porn-movies.html",
    "num_dvds": 53
  },
  {
    "title": "Asia Bootleg",
    "url": "https://www.adultempire.com/28785/studio/asia-bootleg-porn-movies.html",
    "num_dvds": 41
  },
  {
    "title": "Asian District",
    "url": "https://www.adultempire.com/96404/studio/asian-district-porn-movies.html",
    "num_dvds": 29
  },
  {
    "title": "Ass Teen Mouth",
    "url": "https://www.adultempire.com/95867/studio/ass-teen-mouth-porn-movies.html",
    "num_dvds": 29
  },
  {
    "title": "Assence Films",
    "url": "https://www.adultempire.com/93721/studio/assence-films-porn-movies.html",
    "num_dvds": 37
  },
  {
    "title": "ATKingdom",
    "url": "https://www.adultempire.com/92997/studio/atkingdom-porn-movies.html",
    "num_dvds": 576
  },
  {
    "title": "Auntie Trisha",
    "url": "https://www.adultempire.com/95215/studio/auntie-trisha-porn-movies.html",
    "num_dvds": 5
  },
  {
    "title": "Aura Productions",
    "url": "https://www.adultempire.com/93845/studio/aura-productions-porn-movies.html",
    "num_dvds": 541
  },
  {
    "title": "Avalon",
    "url": "https://www.adultempire.com/355/studio/avalon-porn-movies.html",
    "num_dvds": 529
  },
  {
    "title": "Avica",
    "url": "https://www.adultempire.com/335/studio/avica-porn-movies.html",
    "num_dvds": 8
  },
  {
    "title": "Axel Braun Productions",
    "url": "https://www.adultempire.com/93927/studio/axel-braun-productions-porn-movies.html",
    "num_dvds": 10
  },
  {
    "title": "Aziani",
    "url": "https://www.adultempire.com/95110/studio/aziani-porn-movies.html",
    "num_dvds": 44
  },
  {
    "title": "Babes",
    "url": "https://www.adultempire.com/93915/studio/babes-porn-movies.html",
    "num_dvds": 160
  },
  {
    "title": "Baby Doll Pictures",
    "url": "https://www.adultempire.com/26261/studio/baby-doll-pictures-porn-movies.html",
    "num_dvds": 535
  },
  {
    "title": "Bacchus",
    "url": "https://www.adultempire.com/100/studio/bacchus-porn-movies.html",
    "num_dvds": 460
  },
  {
    "title": "Back End Productions",
    "url": "https://www.adultempire.com/32103/studio/back-end-productions-porn-movies.html",
    "num_dvds": 182
  },
  {
    "title": "Bad Ass Pictures",
    "url": "https://www.adultempire.com/92802/studio/bad-ass-pictures-porn-movies.html",
    "num_dvds": 48
  },
  {
    "title": "Bad Daddy POV",
    "url": "https://www.adultempire.com/95310/studio/bad-daddy-pov-porn-movies.html",
    "num_dvds": 73
  },
  {
    "title": "Bad Girl Mafia",
    "url": "https://www.adultempire.com/95473/studio/bad-girl-mafia-porn-movies.html",
    "num_dvds": 11
  },
  {
    "title": "Bad Seed",
    "url": "https://www.adultempire.com/34505/studio/bad-seed-porn-movies.html",
    "num_dvds": 7
  },
  {
    "title": "BAEB",
    "url": "https://www.adultempire.com/95200/studio/baeb-porn-movies.html",
    "num_dvds": 12
  },
  {
    "title": "Banana Jacks",
    "url": "https://www.adultempire.com/95701/studio/banana-jacks-porn-movies.html",
    "num_dvds": 4
  },
  {
    "title": "Bang Bros Productions",
    "url": "https://www.adultempire.com/22914/studio/bang-bros-productions-porn-movies.html",
    "num_dvds": 1590
  },
  {
    "title": "Bang Teen Pussy",
    "url": "https://www.adultempire.com/95869/studio/bang-teen-pussy-porn-movies.html",
    "num_dvds": 16
  },
  {
    "title": "BANG!",
    "url": "https://www.adultempire.com/95207/studio/bang-porn-movies.html",
    "num_dvds": 229
  },
  {
    "title": "Bellapass",
    "url": "https://www.adultempire.com/94788/studio/bellapass-porn-movies.html",
    "num_dvds": 14
  },
  {
    "title": "Bellesa Films",
    "url": "https://www.adultempire.com/95691/studio/bellesa-films-porn-movies.html",
    "num_dvds": 112
  },
  {
    "title": "Bi Empire",
    "url": "https://www.adultempire.com/94763/studio/bi-empire-porn-movies.html",
    "num_dvds": 109
  },
  {
    "title": "Bi Fuck",
    "url": "https://www.adultempire.com/98256/studio/bi-fuck-porn-movies.html",
    "num_dvds": 5
  },
  {
    "title": "Big Boobs Galore",
    "url": "https://www.adultempire.com/94786/studio/big-boobs-galore-porn-movies.html",
    "num_dvds": 5
  },
  {
    "title": "Big Booty Pictures",
    "url": "https://www.adultempire.com/93813/studio/big-booty-pictures-porn-movies.html",
    "num_dvds": 24
  },
  {
    "title": "Big Top",
    "url": "https://www.adultempire.com/102/studio/big-top-porn-movies.html",
    "num_dvds": 340
  },
  {
    "title": "BigBootyTGirls",
    "url": "https://www.adultempire.com/95900/studio/bigbootytgirls-porn-movies.html",
    "num_dvds": 157
  },
  {
    "title": "BiPhoria",
    "url": "https://www.adultempire.com/95556/studio/biphoria-porn-movies.html",
    "num_dvds": 57
  },
  {
    "title": "Bizarre Entertainment",
    "url": "https://www.adultempire.com/202/studio/bizarre-entertainment-porn-movies.html",
    "num_dvds": 387
  },
  {
    "title": "BJRaw",
    "url": "https://www.adultempire.com/96260/studio/bjraw-porn-movies.html",
    "num_dvds": 18
  },
  {
    "title": "Black Fever Films",
    "url": "https://www.adultempire.com/93060/studio/black-fever-films-porn-movies.html",
    "num_dvds": 15
  },
  {
    "title": "Black Ice",
    "url": "https://www.adultempire.com/35000/studio/black-ice-porn-movies.html",
    "num_dvds": 404
  },
  {
    "title": "Black Magic Pictures",
    "url": "https://www.adultempire.com/93119/studio/black-magic-pictures-porn-movies.html",
    "num_dvds": 147
  },
  {
    "title": "Black Market",
    "url": "https://www.adultempire.com/91420/studio/black-market-porn-movies.html",
    "num_dvds": 333
  },
  {
    "title": "Black Planet",
    "url": "https://www.adultempire.com/95526/studio/black-planet-porn-movies.html",
    "num_dvds": 25
  },
  {
    "title": "Blacked",
    "url": "https://www.adultempire.com/94029/studio/blacked-porn-movies.html",
    "num_dvds": 148
  },
  {
    "title": "Blacked Raw",
    "url": "https://www.adultempire.com/95245/studio/blacked-raw-porn-movies.html",
    "num_dvds": 102
  },
  {
    "title": "Blacks on Blondes",
    "url": "https://www.adultempire.com/93488/studio/blacks-on-blondes-porn-movies.html",
    "num_dvds": 318
  },
  {
    "title": "Blazed Studios",
    "url": "https://www.adultempire.com/93917/studio/blazed-studios-porn-movies.html",
    "num_dvds": 186
  },
  {
    "title": "Blu",
    "url": "https://www.adultempire.com/28657/studio/blu-porn-movies.html",
    "num_dvds": 3
  },
  {
    "title": "Blue Pictures",
    "url": "https://www.adultempire.com/93059/studio/blue-pictures-porn-movies.html",
    "num_dvds": 91
  },
  {
    "title": "Blue Vanities",
    "url": "https://www.adultempire.com/93392/studio/blue-vanities-porn-movies.html",
    "num_dvds": 128
  },
  {
    "title": "Bluebird Films",
    "url": "https://www.adultempire.com/93403/studio/bluebird-films-porn-movies.html",
    "num_dvds": 301
  },
  {
    "title": "BlueCity Pictures",
    "url": "https://www.adultempire.com/93906/studio/bluecity-pictures-porn-movies.html",
    "num_dvds": 18
  },
  {
    "title": "Bob's Videos",
    "url": "https://www.adultempire.com/427/studio/bobs-videos-porn-movies.html",
    "num_dvds": 61
  },
  {
    "title": "Body Shoppe Exxxtreme",
    "url": "https://www.adultempire.com/341/studio/body-shoppe-exxxtreme-porn-movies.html",
    "num_dvds": 9
  },
  {
    "title": "Bone Digital",
    "url": "https://www.adultempire.com/93078/studio/bone-digital-porn-movies.html",
    "num_dvds": 70
  },
  {
    "title": "Bouncy Pictures",
    "url": "https://www.adultempire.com/26912/studio/bouncy-pictures-porn-movies.html",
    "num_dvds": 39
  },
  {
    "title": "Box Truck Sex",
    "url": "https://www.adultempire.com/95066/studio/box-truck-sex-porn-movies.html",
    "num_dvds": 6
  },
  {
    "title": "Boy-Girl World",
    "url": "https://www.adultempire.com/93719/studio/boy-girl-world-porn-movies.html",
    "num_dvds": 13
  },
  {
    "title": "Brand-X",
    "url": "https://www.adultempire.com/98304/studio/brand-x-porn-movies.html",
    "num_dvds": 13
  },
  {
    "title": "Brave Films",
    "url": "https://www.adultempire.com/98170/studio/brave-films-porn-movies.html",
    "num_dvds": 19
  },
  {
    "title": "Brazzers",
    "url": "https://www.adultempire.com/93204/studio/brazzers-porn-movies.html",
    "num_dvds": 831
  },
  {
    "title": "British MILF Entertainment",
    "url": "https://www.adultempire.com/94670/studio/british-milf-entertainment-porn-movies.html",
    "num_dvds": 16
  },
  {
    "title": "Brutal Invasion",
    "url": "https://www.adultempire.com/95868/studio/brutal-invasion-porn-movies.html",
    "num_dvds": 19
  },
  {
    "title": "Brutha's Inc.",
    "url": "https://www.adultempire.com/94766/studio/bruthas-inc-porn-movies.html",
    "num_dvds": 26
  },
  {
    "title": "Buddha Bang Productions",
    "url": "https://www.adultempire.com/94838/studio/buddha-bang-productions-porn-movies.html",
    "num_dvds": 36
  },
  {
    "title": "Bukkake Sperm Party",
    "url": "https://www.adultempire.com/95953/studio/bukkake-sperm-party-porn-movies.html",
    "num_dvds": 32
  },
  {
    "title": "Burning Angel",
    "url": "https://www.adultempire.com/92918/studio/burning-angel-porn-movies.html",
    "num_dvds": 53
  },
  {
    "title": "Burning Angel Entertainment",
    "url": "https://www.adultempire.com/90912/studio/burning-angel-entertainment-porn-movies.html",
    "num_dvds": 199
  },
  {
    "title": "Buttman Magazine Choice",
    "url": "https://www.adultempire.com/93362/studio/buttman-magazine-choice-porn-movies.html",
    "num_dvds": 137
  },
  {
    "title": "C Street Corporation",
    "url": "https://www.adultempire.com/34172/studio/c-street-corporation-porn-movies.html",
    "num_dvds": 18
  },
  {
    "title": "Caballero Home Video",
    "url": "https://www.adultempire.com/317/studio/caballero-home-video-porn-movies.html",
    "num_dvds": 770
  },
  {
    "title": "Cal Vista",
    "url": "https://www.adultempire.com/93134/studio/cal-vista-porn-movies.html",
    "num_dvds": 59
  },
  {
    "title": "Cal Vista (Metro)",
    "url": "https://www.adultempire.com/93572/studio/cal-vista-metro-porn-movies.html",
    "num_dvds": 51
  },
  {
    "title": "Catalina Video",
    "url": "https://www.adultempire.com/90563/studio/catalina-video-porn-movies.html",
    "num_dvds": 7
  },
  {
    "title": "Catwalk Poison",
    "url": "https://www.adultempire.com/93666/studio/catwalk-poison-porn-movies.html",
    "num_dvds": 5
  },
  {
    "title": "CAV",
    "url": "https://www.adultempire.com/94/studio/cav-porn-movies.html",
    "num_dvds": 4
  },
  {
    "title": "CAV (Adult)",
    "url": "https://www.adultempire.com/93461/studio/cav-adult-porn-movies.html",
    "num_dvds": 4
  },
  {
    "title": "Celestial",
    "url": "https://www.adultempire.com/404/studio/celestial-porn-movies.html",
    "num_dvds": 103
  },
  {
    "title": "Celluloid Addiction",
    "url": "https://www.adultempire.com/93355/studio/celluloid-addiction-porn-movies.html",
    "num_dvds": 6
  },
  {
    "title": "Cento X Cento",
    "url": "https://www.adultempire.com/94203/studio/cento-x-cento-porn-movies.html",
    "num_dvds": 17
  },
  {
    "title": "Cezar Capone",
    "url": "https://www.adultempire.com/93297/studio/cezar-capone-porn-movies.html",
    "num_dvds": 61
  },
  {
    "title": "Channel 1 Releasing",
    "url": "https://www.adultempire.com/794/studio/channel-1-releasing-porn-movies.html",
    "num_dvds": 3
  },
  {
    "title": "Channel 69",
    "url": "https://www.adultempire.com/217/studio/channel-69-porn-movies.html",
    "num_dvds": 1221
  },
  {
    "title": "Cheaters Club XXX",
    "url": "https://www.adultempire.com/94666/studio/cheaters-club-xxx-porn-movies.html",
    "num_dvds": 23
  },
  {
    "title": "Cherry Boxxx Pictures",
    "url": "https://www.adultempire.com/25303/studio/cherry-boxxx-pictures-porn-movies.html",
    "num_dvds": 481
  },
  {
    "title": "Cherry Pimps",
    "url": "https://www.adultempire.com/93945/studio/cherry-pimps-porn-movies.html",
    "num_dvds": 49
  },
  {
    "title": "Cherry Pop",
    "url": "https://www.adultempire.com/95042/studio/cherry-pop-porn-movies.html",
    "num_dvds": 28
  },
  {
    "title": "Cinderella",
    "url": "https://www.adultempire.com/375/studio/cinderella-porn-movies.html",
    "num_dvds": 260
  },
  {
    "title": "Cinderella Classics",
    "url": "https://www.adultempire.com/93864/studio/cinderella-classics-porn-movies.html",
    "num_dvds": 16
  },
  {
    "title": "Cinema Erotika",
    "url": "https://www.adultempire.com/93890/studio/cinema-erotika-porn-movies.html",
    "num_dvds": 8
  },
  {
    "title": "Climax Films",
    "url": "https://www.adultempire.com/94161/studio/climax-films-porn-movies.html",
    "num_dvds": 129
  },
  {
    "title": "Club",
    "url": "https://www.adultempire.com/90137/studio/club-porn-movies.html",
    "num_dvds": 3
  },
  {
    "title": "Club 59 / Elegant Angel",
    "url": "https://www.adultempire.com/93560/studio/club-59-elegant-angel-porn-movies.html",
    "num_dvds": 14
  },
  {
    "title": "Club Jenna",
    "url": "https://www.adultempire.com/531/studio/club-jenna-porn-movies.html",
    "num_dvds": 105
  },
  {
    "title": "Club Mama",
    "url": "https://www.adultempire.com/98166/studio/club-mama-porn-movies.html",
    "num_dvds": 22
  },
  {
    "title": "ClubCastings",
    "url": "https://www.adultempire.com/96302/studio/clubcastings-porn-movies.html",
    "num_dvds": 7
  },
  {
    "title": "Coast To Coast",
    "url": "https://www.adultempire.com/104/studio/coast-to-coast-porn-movies.html",
    "num_dvds": 262
  },
  {
    "title": "Colette",
    "url": "https://www.adultempire.com/94680/studio/colette-porn-movies.html",
    "num_dvds": 21
  },
  {
    "title": "Collateral Damage",
    "url": "https://www.adultempire.com/28656/studio/collateral-damage-porn-movies.html",
    "num_dvds": 10
  },
  {
    "title": "Combat Zone",
    "url": "https://www.adultempire.com/85941/studio/combat-zone-porn-movies.html",
    "num_dvds": 394
  },
  {
    "title": "Concoxxxion",
    "url": "https://www.adultempire.com/95763/studio/concoxxxion-porn-movies.html",
    "num_dvds": 29
  },
  {
    "title": "Corbin Fisher",
    "url": "https://www.adultempire.com/94273/studio/corbin-fisher-porn-movies.html",
    "num_dvds": 19
  },
  {
    "title": "Cougar Kingdom",
    "url": "https://www.adultempire.com/94092/studio/cougar-kingdom-porn-movies.html",
    "num_dvds": 8
  },
  {
    "title": "Crave Media",
    "url": "https://www.adultempire.com/95208/studio/crave-media-porn-movies.html",
    "num_dvds": 214
  },
  {
    "title": "Cream of the Crop",
    "url": "https://www.adultempire.com/94492/studio/cream-of-the-crop-porn-movies.html",
    "num_dvds": 6
  },
  {
    "title": "Creation Of Adam",
    "url": "https://www.adultempire.com/94094/studio/creation-of-adam-porn-movies.html",
    "num_dvds": 4
  },
  {
    "title": "Critical Mass Video",
    "url": "https://www.adultempire.com/93328/studio/critical-mass-video-porn-movies.html",
    "num_dvds": 19
  },
  {
    "title": "Crush Girls",
    "url": "https://www.adultempire.com/95485/studio/crush-girls-porn-movies.html",
    "num_dvds": 7
  },
  {
    "title": "Culioneros",
    "url": "https://www.adultempire.com/94817/studio/culioneros-porn-movies.html",
    "num_dvds": 95
  },
  {
    "title": "Cult Epics (XXX)",
    "url": "https://www.adultempire.com/93414/studio/cult-epics-xxx-porn-movies.html",
    "num_dvds": 3
  },
  {
    "title": "CumLouder",
    "url": "https://www.adultempire.com/93967/studio/cumlouder-porn-movies.html",
    "num_dvds": 137
  },
  {
    "title": "Cutie Pie",
    "url": "https://www.adultempire.com/95312/studio/cutie-pie-porn-movies.html",
    "num_dvds": 298
  },
  {
    "title": "Cutiepie Films",
    "url": "https://www.adultempire.com/94117/studio/cutiepie-films-porn-movies.html",
    "num_dvds": 15
  },
  {
    "title": "Cutting Edge",
    "url": "https://www.adultempire.com/93073/studio/cutting-edge-porn-movies.html",
    "num_dvds": 19
  },
  {
    "title": "Dancing Llama",
    "url": "https://www.adultempire.com/94141/studio/dancing-llama-porn-movies.html",
    "num_dvds": 10
  },
  {
    "title": "Dane Jones",
    "url": "https://www.adultempire.com/93820/studio/dane-jones-porn-movies.html",
    "num_dvds": 156
  },
  {
    "title": "Dane Productions",
    "url": "https://www.adultempire.com/392/studio/dane-productions-porn-movies.html",
    "num_dvds": 9
  },
  {
    "title": "Daring",
    "url": "https://www.adultempire.com/95511/studio/daring-porn-movies.html",
    "num_dvds": 4
  },
  {
    "title": "Daring Media Group DVD",
    "url": "https://www.adultempire.com/93278/studio/daring-media-group-dvd-porn-movies.html",
    "num_dvds": 126
  },
  {
    "title": "Darius Caine Productions",
    "url": "https://www.adultempire.com/93131/studio/darius-caine-productions-porn-movies.html",
    "num_dvds": 3
  },
  {
    "title": "Darkside Entertainment",
    "url": "https://www.adultempire.com/574/studio/darkside-entertainment-porn-movies.html",
    "num_dvds": 294
  },
  {
    "title": "DarkX",
    "url": "https://www.adultempire.com/94675/studio/darkx-porn-movies.html",
    "num_dvds": 89
  },
  {
    "title": "Dave Pounder Productions",
    "url": "https://www.adultempire.com/28976/studio/dave-pounder-productions-porn-movies.html",
    "num_dvds": 11
  },
  {
    "title": "DD Busty",
    "url": "https://www.adultempire.com/93983/studio/dd-busty-porn-movies.html",
    "num_dvds": 64
  },
  {
    "title": "DDF Network",
    "url": "https://www.adultempire.com/95714/studio/ddf-network-porn-movies.html",
    "num_dvds": 150
  },
  {
    "title": "DDF Video",
    "url": "https://www.adultempire.com/93936/studio/ddf-video-porn-movies.html",
    "num_dvds": 27
  },
  {
    "title": "Deep Lush",
    "url": "https://www.adultempire.com/98239/studio/deep-lush-porn-movies.html",
    "num_dvds": 37
  },
  {
    "title": "Deeper",
    "url": "https://www.adultempire.com/95762/studio/deeper-porn-movies.html",
    "num_dvds": 80
  },
  {
    "title": "DEF Entertainment",
    "url": "https://www.adultempire.com/93806/studio/def-entertainment-porn-movies.html",
    "num_dvds": 64
  },
  {
    "title": "Depraved Life",
    "url": "https://www.adultempire.com/95235/studio/depraved-life-porn-movies.html",
    "num_dvds": 26
  },
  {
    "title": "Desire Films",
    "url": "https://www.adultempire.com/94051/studio/desire-films-porn-movies.html",
    "num_dvds": 279
  },
  {
    "title": "Desire Media",
    "url": "https://www.adultempire.com/93891/studio/desire-media-porn-movies.html",
    "num_dvds": 44
  },
  {
    "title": "Desperate Pleasures",
    "url": "https://www.adultempire.com/93991/studio/desperate-pleasures-porn-movies.html",
    "num_dvds": 357
  }
]